{
  "folder": "V4skAU6G3OH5fXgE",
  "name": "Fiery Footwork",
  "type": "effect",
  "system": {
    "_migration": {
      "version": 0.111,
      "previous": null
    },
    "publication": {
      "source": "",
      "authors": [],
      "notes": ""
    },
    "traits": []
  },
  "img": "icons/magic/movement/trail-streak-impact-blue.webp",
  "effects": [
    {
      "name": "Fiery Footwork",
      "type": "affliction",
      "_id": "Dg8cxxwMd6jg7qLk",
      "img": "icons/magic/movement/trail-streak-impact-blue.webp",
      "system": {
        "changes": [
          {
            "type": "basic",
            "key": "system.movement.overland.value",
            "value": 4,
            "predicate": [],
            "mode": 2,
            "ignored": false
          },
          {
            "type": "basic",
            "key": "system.movement.flight.value",
            "value": 4,
            "predicate": [],
            "mode": 2,
            "ignored": false
          }
        ],
        "slug": null,
        "traits": [],
        "removeAfterCombat": true,
        "removeOnRecall": false,
        "removeAfterAttacking": true,
        "removeAfterAttacked": false,
        "stacks": 0,
        "priority": 50,
        "formula": "-1/16",
        "type": "damage"
      },
      "disabled": false,
      "duration": {
        "startTime": null,
        "combat": null,
        "turns": null,
        "startTurn": null
      },
      "description": "",
      "origin": null,
      "tint": "#ffffff",
      "transfer": true,
      "statuses": [],
      "sort": 0,
      "flags": {
        "ptr2e": {
          "displayOnToken": "always"
        }
      },
      "_stats": {
        "compendiumSource": null,
        "duplicateSource": null,
        "exportSource": null,
        "coreVersion": "13.347",
        "systemId": "ptr2e",
        "systemVersion": "1.4.3.beta",
        "lastModifiedBy": null
      }
    }
  ],
  "flags": {},
  "_id": "5r2IITbEOGcERZxf"
}