{
  "name": "Migration Formation",
  "_id": "Noct5eyeZ1ElQMbJ",
  "type": "perk",
  "img": "systems/ptr2e/img/svg/flying_icon.svg",
  "effects": [],
  "system": {
    "_migration": {
      "version": 0.111,
      "previous": null
    },
    "publication": {
      "source": "PTR2e Core",
      "authors": [
        "Dragoon"
      ],
      "notes": ""
    },
    "actions": [],
    "slug": "migration-formation",
    "description": "<div data-testid=\"markdown-body\" data-team-hovercards-enabled=\"true\" class=\"markdown-body\" data-turbolinks=\"false\"><div class=\"Box-sc-g0xbh4-0 markdown-body NewMarkdownViewer-module__safe-html-box--cRsz0\"><p dir=\"auto\">Effect: When the user declares Rush, Leap, Jump, or Breach, all allies within double the user’s Reach may freely use the same Action after the user resolves the triggering Action.</p></div></div><div class=\"IssueBodyViewer-module__IssueBodyTaskList--r4XEH\"><div class=\"IssueBodyViewer-module__IssueBodySubIssueButtonContainer--EZm50\"><div class=\"AddSubIssueButtonGroup-module__Box--Txhdj\"><div class=\"Box-sc-g0xbh4-0 prc-ButtonGroup-ButtonGroup-vcMeG\"><div><p></p></div><p></p></div></div></div></div>",
    "traits": [],
    "prerequisites": [
      "trait:flying"
    ],
    "autoUnlock": [],
    "cost": 1,
    "design": {
      "arena": "physical",
      "approach": "finesse",
      "archetype": "flying"
    },
    "global": true,
    "webs": [],
    "nodes": [
      {
        "x": 121,
        "y": 58,
        "hidden": false,
        "type": "normal",
        "connected": [
          "minor-buff-59",
          "minor-buff-60",
          "wingblades"
        ],
        "config": {
          "texture": "systems/ptr2e/img/svg/flying_icon.svg",
          "backgroundColor": null,
          "borderColor": null,
          "tint": null
        },
        "tier": null
      }
    ]
  },
  "folder": "QFi3YFwyLLQSpOap"
}