{
  "name": "Slow Orb",
  "img": "systems/ptr2e/img/icons/consumable_icon.webp",
  "type": "consumable",
  "system": {
    "cost": 4,
    "crafting": {
      "skill": "handiwork",
      "spans": null,
      "materials": []
    },
    "equipped": {
      "slot": "belt",
      "carryType": "stowed",
      "handsHeld": null
    },
    "grade": "C",
    "fling": {
      "type": "untyped",
      "power": 40,
      "accuracy": 100,
      "hide": false,
      "range": {
        "target": "creature",
        "distance": 10,
        "unit": "m"
      }
    },
    "rarity": "common",
    "consumableType": "other",
    "traits": [
      "combat",
      "consumable",
      "wonder-orb"
    ],
    "description": "<p>All foes in the Room gain @Affliction[slowed 5].</p>",
    "quantity": 1,
    "slug": "slow-orb",
    "stack": 1,
    "_migration": {
      "version": null,
      "previous": null
    },
    "publication": {
      "source": "PTR 2e Core",
      "authors": [
        "PTR 2e Team"
      ],
      "notes": ""
    },
    "actions": [
      {
        "name": "Slow Orb",
        "slug": "slow-orb",
        "description": "<p>All foes in the Room gain @Affliction[slowed 5].</p>",
        "traits": [
          "combat",
          "consumable",
          "wonder-orb"
        ],
        "type": "generic",
        "img": "systems/ptr2e/img/icons/consumable_icon.webp",
        "cost": {
          "activation": "complex"
        },
        "range": {
          "target": "field",
          "unit": "m"
        }
      }
    ]
  },
  "_id": "jQaGwJVcHkNc8Jyj",
  "effects": [
    {
      "name": "Slow Orb",
      "type": "passive",
      "_id": "bIvhasnfrxvLc5Jn",
      "img": "systems/ptr2e/img/icons/effect_icon.webp",
      "system": {
        "changes": [
          {
            "type": "roll-effect",
            "key": "slow-orb-generic",
            "value": "Compendium.ptr2e.core-effects.Item.slowedcondititem",
            "predicate": [],
            "chance": 100,
            "isFixedChance": false,
            "affects": "target",
            "alterations": [],
            "dontMerge": false,
            "mode": 2,
            "ignored": false
          }
        ],
        "slug": null,
        "traits": [],
        "removeAfterCombat": true,
        "removeOnRecall": false,
        "removeAfterAttacking": false,
        "removeAfterAttacked": false,
        "stacks": 0
      },
      "disabled": false,
      "duration": {
        "startTime": null,
        "combat": null
      },
      "description": "",
      "origin": null,
      "tint": "#ffffff",
      "transfer": true,
      "statuses": [],
      "sort": 0,
      "flags": {
        "ptr2e": {
          "displayOnToken": ""
        }
      },
      "_stats": {
        "compendiumSource": null,
        "duplicateSource": null,
        "exportSource": null,
        "coreVersion": "13.348",
        "systemId": "ptr2e",
        "systemVersion": "1.4.4.beta",
        "createdTime": 1758758264084,
        "modifiedTime": 1758758283510,
        "lastModifiedBy": "mK35yvCqCgiTUvKf"
      }
    }
  ],
  "folder": "4MbEHvhwmG5DYTkB"
}