{
  "name": "cobalion",
  "type": "species",
  "img": "systems/ptr2e/img/icons/species_icon.webp",
  "system": {
    "number": 638,
    "size": {
      "category": "large",
      "type": "height",
      "height": 2.1,
      "weight": 250
    },
    "diet": [
      "herbivore"
    ],
    "movement": [
      {
        "type": "overland",
        "value": 16
      },
      {
        "type": "swim",
        "value": 8
      }
    ],
    "traits": [
      "pokemon",
      "legendary",
      "bladed",
      "well-built",
      "natural-steel",
      "aura-user",
      "darkvision-15",
      "fully-evolved",
      "jump-5"
    ],
    "abilities": {
      "starting": [
        {
          "slug": "righteous-blade"
        }
      ],
      "basic": [
        {
          "slug": "justified"
        },
        {
          "slug": "sharpness"
        }
      ],
      "advanced": [
        {
          "slug": "friend-guard"
        },
        {
          "slug": "sweeping-edge"
        }
      ],
      "master": [
        {
          "slug": "avenger"
        },
        {
          "slug": "magic-guard"
        }
      ]
    },
    "skills": [
      {
        "slug": "acrobatics",
        "value": 65,
        "rvs": 0,
        "favourite": false,
        "hidden": false,
        "group": null
      },
      {
        "slug": "appraise",
        "value": 35,
        "rvs": 0,
        "favourite": false,
        "hidden": false,
        "group": null
      },
      {
        "slug": "archaeology",
        "value": 30,
        "rvs": 0,
        "favourite": false,
        "hidden": false,
        "group": null
      },
      {
        "slug": "aura-sense",
        "value": 30,
        "rvs": 0,
        "favourite": false,
        "hidden": false,
        "group": null
      },
      {
        "slug": "climb",
        "value": 65,
        "rvs": 0,
        "favourite": false,
        "hidden": false,
        "group": null
      },
      {
        "slug": "conversation",
        "value": 70,
        "rvs": 0,
        "favourite": false,
        "hidden": false,
        "group": null
      },
      {
        "slug": "fast-talk",
        "value": 40,
        "rvs": 0,
        "favourite": false,
        "hidden": false,
        "group": null
      },
      {
        "slug": "history",
        "value": 50,
        "rvs": 0,
        "favourite": false,
        "hidden": false,
        "group": null
      },
      {
        "slug": "husbandry",
        "value": 60,
        "rvs": 0,
        "favourite": false,
        "hidden": false,
        "group": null
      },
      {
        "slug": "intimidate",
        "value": 65,
        "rvs": 0,
        "favourite": false,
        "hidden": false,
        "group": null
      },
      {
        "slug": "leadership",
        "value": 80,
        "rvs": 0,
        "favourite": false,
        "hidden": false,
        "group": null
      },
      {
        "slug": "legal",
        "value": 30,
        "rvs": 0,
        "favourite": false,
        "hidden": false,
        "group": null
      },
      {
        "slug": "legendary",
        "value": 40,
        "rvs": 0,
        "favourite": false,
        "hidden": false,
        "group": null
      },
      {
        "slug": "lift",
        "value": 65,
        "rvs": 0,
        "favourite": false,
        "hidden": false,
        "group": null
      },
      {
        "slug": "listen",
        "value": 65,
        "rvs": 0,
        "favourite": false,
        "hidden": false,
        "group": null
      },
      {
        "slug": "medicine",
        "value": 40,
        "rvs": 0,
        "favourite": false,
        "hidden": false,
        "group": null
      },
      {
        "slug": "navigate",
        "value": 60,
        "rvs": 0,
        "favourite": false,
        "hidden": false,
        "group": null
      },
      {
        "slug": "negotiation",
        "value": 75,
        "rvs": 0,
        "favourite": false,
        "hidden": false,
        "group": null
      },
      {
        "slug": "psychology",
        "value": 40,
        "rvs": 0,
        "favourite": false,
        "hidden": false,
        "group": null
      },
      {
        "slug": "running",
        "value": 65,
        "rvs": 0,
        "favourite": false,
        "hidden": false,
        "group": null
      },
      {
        "slug": "spot",
        "value": 75,
        "rvs": 0,
        "favourite": false,
        "hidden": false,
        "group": null
      },
      {
        "slug": "stealth",
        "value": 45,
        "rvs": 0,
        "favourite": false,
        "hidden": false,
        "group": null
      },
      {
        "slug": "survival",
        "value": 70,
        "rvs": 0,
        "favourite": false,
        "hidden": false,
        "group": null
      },
      {
        "slug": "swim",
        "value": 45,
        "rvs": 0,
        "favourite": false,
        "hidden": false,
        "group": null
      },
      {
        "slug": "teaching",
        "value": 60,
        "rvs": 0,
        "favourite": false,
        "hidden": false,
        "group": null
      },
      {
        "slug": "track",
        "value": 65,
        "rvs": 0,
        "favourite": false,
        "hidden": false,
        "group": null
      }
    ],
    "slug": "cobalion",
    "stats": {
      "hp": 91,
      "atk": 90,
      "def": 129,
      "spa": 90,
      "spd": 72,
      "spe": 108
    },
    "types": [
      "fighting",
      "steel"
    ],
    "moves": {
      "levelUp": [
        {
          "name": "helping-hand",
          "gen": "scarlet-violet",
          "level": 1
        },
        {
          "name": "leer",
          "gen": "scarlet-violet",
          "level": 1
        },
        {
          "name": "quick-attack",
          "gen": "scarlet-violet",
          "level": 1
        },
        {
          "name": "work-up",
          "gen": "scarlet-violet",
          "level": 1
        },
        {
          "name": "metal-claw",
          "gen": "scarlet-violet",
          "level": 7
        },
        {
          "name": "quick-guard",
          "gen": "scarlet-violet",
          "level": 14
        },
        {
          "name": "double-kick",
          "gen": "scarlet-violet",
          "level": 21
        },
        {
          "name": "retaliate",
          "gen": "scarlet-violet",
          "level": 28
        },
        {
          "name": "metal-burst",
          "gen": "scarlet-violet",
          "level": 35
        },
        {
          "name": "take-down",
          "gen": "scarlet-violet",
          "level": 42
        },
        {
          "name": "sacred-sword",
          "gen": "scarlet-violet",
          "level": 49
        },
        {
          "name": "swords-dance",
          "gen": "scarlet-violet",
          "level": 56
        },
        {
          "name": "iron-head",
          "gen": "scarlet-violet",
          "level": 63
        },
        {
          "name": "close-combat",
          "gen": "scarlet-violet",
          "level": 70
        }
      ],
      "tutor": [
        {
          "name": "aerial-ace",
          "gen": "scarlet-violet"
        },
        {
          "name": "air-slash",
          "gen": "scarlet-violet"
        },
        {
          "name": "aura-sphere",
          "gen": "scarlet-violet"
        },
        {
          "name": "block",
          "gen": "ultra-sun-ultra-moon"
        },
        {
          "name": "body-press",
          "gen": "scarlet-violet"
        },
        {
          "name": "body-slam",
          "gen": "scarlet-violet"
        },
        {
          "name": "bounce",
          "gen": "ultra-sun-ultra-moon"
        },
        {
          "name": "brick-break",
          "gen": "scarlet-violet"
        },
        {
          "name": "calm-mind",
          "gen": "scarlet-violet"
        },
        {
          "name": "coaching",
          "gen": "sword-shield"
        },
        {
          "name": "confide",
          "gen": "ultra-sun-ultra-moon"
        },
        {
          "name": "cut",
          "gen": "omega-ruby-alpha-sapphire"
        },
        {
          "name": "double-edge",
          "gen": "scarlet-violet"
        },
        {
          "name": "double-team",
          "gen": "ultra-sun-ultra-moon"
        },
        {
          "name": "endure",
          "gen": "scarlet-violet"
        },
        {
          "name": "facade",
          "gen": "scarlet-violet"
        },
        {
          "name": "false-swipe",
          "gen": "scarlet-violet"
        },
        {
          "name": "flash-cannon",
          "gen": "scarlet-violet"
        },
        {
          "name": "focus-blast",
          "gen": "scarlet-violet"
        },
        {
          "name": "frustration",
          "gen": "ultra-sun-ultra-moon"
        },
        {
          "name": "giga-impact",
          "gen": "scarlet-violet"
        },
        {
          "name": "heavy-slam",
          "gen": "scarlet-violet"
        },
        {
          "name": "hidden-power",
          "gen": "ultra-sun-ultra-moon"
        },
        {
          "name": "hone-claws",
          "gen": "omega-ruby-alpha-sapphire"
        },
        {
          "name": "hyper-beam",
          "gen": "scarlet-violet"
        },
        {
          "name": "iron-defense",
          "gen": "ultra-sun-ultra-moon"
        },
        {
          "name": "laser-focus",
          "gen": "ultra-sun-ultra-moon"
        },
        {
          "name": "magnet-rise",
          "gen": "ultra-sun-ultra-moon"
        },
        {
          "name": "megahorn",
          "gen": "sword-shield"
        },
        {
          "name": "metal-sound",
          "gen": "scarlet-violet"
        },
        {
          "name": "poison-jab",
          "gen": "scarlet-violet"
        },
        {
          "name": "protect",
          "gen": "scarlet-violet"
        },
        {
          "name": "psych-up",
          "gen": "scarlet-violet"
        },
        {
          "name": "rain-dance",
          "gen": "scarlet-violet"
        },
        {
          "name": "reflect",
          "gen": "scarlet-violet"
        },
        {
          "name": "rest",
          "gen": "scarlet-violet"
        },
        {
          "name": "return",
          "gen": "ultra-sun-ultra-moon"
        },
        {
          "name": "revenge",
          "gen": "sword-shield"
        },
        {
          "name": "reversal",
          "gen": "scarlet-violet"
        },
        {
          "name": "roar",
          "gen": "scarlet-violet"
        },
        {
          "name": "rock-polish",
          "gen": "ultra-sun-ultra-moon"
        },
        {
          "name": "rock-smash",
          "gen": "omega-ruby-alpha-sapphire"
        },
        {
          "name": "round",
          "gen": "sword-shield"
        },
        {
          "name": "safeguard",
          "gen": "sword-shield"
        },
        {
          "name": "sandstorm",
          "gen": "scarlet-violet"
        },
        {
          "name": "scary-face",
          "gen": "scarlet-violet"
        },
        {
          "name": "secret-power",
          "gen": "omega-ruby-alpha-sapphire"
        },
        {
          "name": "sleep-talk",
          "gen": "black-2-white-2"
        },
        {
          "name": "smart-strike",
          "gen": "scarlet-violet"
        },
        {
          "name": "snore",
          "gen": "ultra-sun-ultra-moon"
        },
        {
          "name": "stealth-rock",
          "gen": "ultra-sun-ultra-moon"
        },
        {
          "name": "steel-beam",
          "gen": "sword-shield"
        },
        {
          "name": "stone-edge",
          "gen": "scarlet-violet"
        },
        {
          "name": "strength",
          "gen": "omega-ruby-alpha-sapphire"
        },
        {
          "name": "substitute",
          "gen": "scarlet-violet"
        },
        {
          "name": "sunny-day",
          "gen": "scarlet-violet"
        },
        {
          "name": "superpower",
          "gen": "ultra-sun-ultra-moon"
        },
        {
          "name": "swagger",
          "gen": "ultra-sun-ultra-moon"
        },
        {
          "name": "swift",
          "gen": "scarlet-violet"
        },
        {
          "name": "taunt",
          "gen": "scarlet-violet"
        },
        {
          "name": "tera-blast",
          "gen": "scarlet-violet"
        },
        {
          "name": "thunder-wave",
          "gen": "scarlet-violet"
        },
        {
          "name": "toxic",
          "gen": "ultra-sun-ultra-moon"
        },
        {
          "name": "upper-hand",
          "gen": "scarlet-violet"
        },
        {
          "name": "vacuum-wave",
          "gen": "scarlet-violet"
        },
        {
          "name": "volt-switch",
          "gen": "scarlet-violet"
        },
        {
          "name": "x-scissor",
          "gen": "scarlet-violet"
        },
        {
          "name": "zen-headbutt",
          "gen": "ultra-sun-ultra-moon"
        }
      ]
    },
    "captureRate": 9,
    "eggGroups": [
      "no-eggs"
    ],
    "genderRatio": -1,
    "habitats": [],
    "evolutions": {
      "name": "cobalion",
      "details": null,
      "evolutions": [],
      "uuid": null,
      "methods": [],
      "perk": {
        "x": 26,
        "y": 26
      }
    },
    "publication": {
      "source": "PTR 2e Core - Unova Dex",
      "authors": [
        "PTR 2e Team"
      ],
      "notes": ""
    },
    "_migration": {
      "version": null,
      "previous": null
    }
  },
  "_id": "SvXqmcN3eqBNXWZT",
  "effects": []
}