{
  "name": "Keyword Demo \u2013 Crash 1 2",
  "description": "Autogenerated scenario highlighting the Crash 1 2 keyword via High Jump Kick. Launch with `auto-ptu play keyword_demos/crash-1-2_demo`.",
  "default_weather": "Clear",
  "grid": {
    "width": 10,
    "height": 6,
    "blockers": [],
    "tiles": {}
  },
  "players": [
    {
      "name": "Keyword Ace",
      "species": "Keyword Ace",
      "level": 30,
      "types": [
        "Fighting"
      ],
      "hp_stat": 15,
      "atk": 12,
      "def": 12,
      "spatk": 12,
      "spdef": 12,
      "spd": 12,
      "moves": [
        {
          "name": "High Jump Kick",
          "type": "Fighting",
          "category": "Physical",
          "db": 13,
          "ac": 3,
          "range_kind": "Melee",
          "range_value": 1,
          "target_kind": "Melee",
          "target_range": 1,
          "area_kind": null,
          "area_value": null,
          "freq": "EOT",
          "keywords": [
            "crash-1-2"
          ],
          "priority": 0,
          "crit_range": 20,
          "range_text": "Melee, Dash, 1 Target / Melee 1, Trait: Crash 1 2",
          "effects_text": "If High Jump Kick misses, the user loses Hit Points equal to 1/4th of their Max Hit Points. A failure to hit due to a Move with the Shield keyword does not count as a miss. This cannot be used if Gravity is in effect.\n\nThis attack highlights the Crash 1 2 keyword imported from Foundry."
        },
        {
          "name": "Tackle",
          "type": "Normal",
          "category": "Physical",
          "db": 6,
          "ac": 2,
          "range_kind": "Melee",
          "range_value": 1,
          "target_kind": "Melee",
          "target_range": 1,
          "freq": "At-Will",
          "range_text": "Melee 1",
          "effects_text": "Fallback basic attack."
        }
      ],
      "movement": {
        "overland": 6,
        "sky": 0,
        "swim": 4,
        "levitate": 0,
        "burrow": 0,
        "h_jump": 2,
        "l_jump": 2,
        "power": 4
      }
    }
  ],
  "foes": [
    {
      "name": "Target Dummy",
      "species": "Target Dummy",
      "level": 28,
      "types": [
        "Normal"
      ],
      "hp_stat": 12,
      "atk": 8,
      "def": 8,
      "spatk": 8,
      "spdef": 8,
      "spd": 6,
      "moves": [
        {
          "name": "Harden",
          "type": "Normal",
          "category": "Status",
          "db": 0,
          "ac": null,
          "range_kind": "Self",
          "range_value": 0,
          "target_kind": "Self",
          "target_range": 0,
          "freq": "At-Will",
          "range_text": "Self",
          "effects_text": "The dummy braces for impact."
        }
      ],
      "movement": {
        "overland": 4,
        "sky": 0,
        "swim": 2,
        "levitate": 0,
        "burrow": 0,
        "h_jump": 1,
        "l_jump": 1,
        "power": 2
      }
    }
  ]
}
